huqt_oracle_client/__init__.py
huqt_oracle_client/client.py
huqt_oracle_client/constants.py
huqt_oracle_client/game.py
huqt_oracle_client/protos/__init__.py
huqt_oracle_client/protos/admin_pb2.py
huqt_oracle_client/protos/admin_pb2_grpc.py
huqt_oracle_client/protos/exchange_pb2.py
huqt_oracle_client/protos/exchange_pb2_grpc.py
huqt_oracle_client/protos/marketdata_pb2.py
huqt_oracle_client/protos/marketdata_pb2_grpc.py
huqtoracleclient-0.5.0.dist-info/licenses/LICENSE
huqtoracleclient-0.5.0.dist-info/METADATA
huqtoracleclient-0.5.0.dist-info/WHEEL
huqtoracleclient-0.5.0.dist-info/top_level.txt
huqtoracleclient-0.5.0.dist-info/RECORD
